tensorpy/__init__.py
tensorpy/classify.py
tensorpy/classify_image.py
tensorpy/download_imagenet.py
tensorpy/image_base.py
tensorpy/settings.py
tensorpy/web_core.py
tensorpy-1.6.1.dist-info/LICENSE
tensorpy-1.6.1.dist-info/METADATA
tensorpy-1.6.1.dist-info/WHEEL
tensorpy-1.6.1.dist-info/entry_points.txt
tensorpy-1.6.1.dist-info/top_level.txt
tensorpy-1.6.1.dist-info/RECORD
