Metadata-Version: 2.1
Name: tensorpy
Version: 1.6.1
Summary: Easy Image Classification with TensorFlow!
Home-page: https://github.com/TensorPy/TensorPy
Author: Michael Mintz
Author-email: mdmintz@gmail.com
Maintainer: Michael Mintz
License: MIT
Platform: Linux
Platform: Unix
Platform: Mac OS-X
Classifier: Programming Language :: Python :: 3.5
Classifier: Programming Language :: Python :: 3.6
Classifier: Programming Language :: Python :: 3.7
Requires-Python: >=3.5, <3.8
Requires-Dist: tensorflow (==1.15.4)
Requires-Dist: pip (>=20.2.3)
Requires-Dist: six (>=1.15.0)
Requires-Dist: requests (>=2.24.0)
Requires-Dist: Pillow (==7.2.0)
Requires-Dist: beautifulsoup4 (==4.9.2)
